napari_imsmicrolink/__init__.py
napari_imsmicrolink/_dock_widget.py
napari_imsmicrolink/_version.py
napari_imsmicrolink/napari.yaml
napari_imsmicrolink/_tests/__init__.py
napari_imsmicrolink/_tests/test_dock_widget.py
napari_imsmicrolink/_tests/data_tests/__init__.py
napari_imsmicrolink/_tests/data_tests/test_image_transform.py
napari_imsmicrolink/_tests/data_tests/test_ims_pixel_map.py
napari_imsmicrolink/_tests/data_tests/test_microscopy_reader.py
napari_imsmicrolink/_tests/data_tests/test_microscopy_writer.py
napari_imsmicrolink/_tests/utils_tests/__init__.py
napari_imsmicrolink/_tests/utils_tests/test_utils.py
napari_imsmicrolink/data/__init__.py
napari_imsmicrolink/data/czi_reader.py
napari_imsmicrolink/data/image_transform.py
napari_imsmicrolink/data/ims_pixel_map.py
napari_imsmicrolink/data/microscopy_reader.py
napari_imsmicrolink/data/microscopy_writer.py
napari_imsmicrolink/data/tifffile_reader.py
napari_imsmicrolink/qwidgets/__init__.py
napari_imsmicrolink/qwidgets/data_ctl_group.py
napari_imsmicrolink/qwidgets/ims_ctl_group.py
napari_imsmicrolink/qwidgets/save_ctl_group.py
napari_imsmicrolink/qwidgets/save_dialog.py
napari_imsmicrolink/qwidgets/tform_ctl_group.py
napari_imsmicrolink/qwidgets/subwidgets/__init__.py
napari_imsmicrolink/qwidgets/subwidgets/add_micro_info.py
napari_imsmicrolink/qwidgets/subwidgets/control_ims_info.py
napari_imsmicrolink/qwidgets/subwidgets/control_rotation.py
napari_imsmicrolink/qwidgets/subwidgets/control_save.py
napari_imsmicrolink/qwidgets/subwidgets/control_transform.py
napari_imsmicrolink/qwidgets/subwidgets/ims_add_info.py
napari_imsmicrolink/utils/__init__.py
napari_imsmicrolink/utils/color.py
napari_imsmicrolink/utils/coords.py
napari_imsmicrolink/utils/czi.py
napari_imsmicrolink/utils/file.py
napari_imsmicrolink/utils/image.py
napari_imsmicrolink/utils/ims_coords.py
napari_imsmicrolink/utils/json.py
napari_imsmicrolink/utils/ome.py
napari_imsmicrolink/utils/points.py
napari_imsmicrolink/utils/tifffile_meta.py
napari_imsmicrolink-0.1.9.dist-info/LICENSE
napari_imsmicrolink-0.1.9.dist-info/METADATA
napari_imsmicrolink-0.1.9.dist-info/WHEEL
napari_imsmicrolink-0.1.9.dist-info/entry_points.txt
napari_imsmicrolink-0.1.9.dist-info/top_level.txt
napari_imsmicrolink-0.1.9.dist-info/RECORD
