Metadata-Version: 2.1
Name: napari-imsmicrolink
Version: 0.1.9
Summary: Plugin to perform IMS to microscopy registration using laser ablation marks.
Home-page: https://github.com/nhpatterson/napari-imsmicrolink
Author: Nathan Heath Patterson
Author-email: heath.patterson@vanderbilt.edu
License: MIT
Project-URL: Bug Tracker, https://github.com/nhpatterson/napari-imsmicrolink/issues
Project-URL: Documentation, https://github.com/nhpatterson/napari-imsmicrolink#README.md
Project-URL: Source Code, https://github.com/nhpatterson/napari-imsmicrolink
Project-URL: User Support, https://github.com/nhpatterson/napari-imsmicrolink/issues
Classifier: Development Status :: 3 - Alpha
Classifier: Intended Audience :: Developers
Classifier: Framework :: napari
Classifier: Topic :: Software Development :: Testing
Classifier: Programming Language :: Python
Classifier: Programming Language :: Python :: 3
Classifier: Programming Language :: Python :: 3.8
Classifier: Programming Language :: Python :: 3.9
Classifier: Programming Language :: Python :: 3.10
Classifier: Operating System :: OS Independent
Classifier: License :: OSI Approved :: MIT License
Requires-Python: >=3.8
License-File: LICENSE
Requires-Dist: numpy
Requires-Dist: tifffile
Requires-Dist: dask
Requires-Dist: zarr (>=2.10.3)
Requires-Dist: qtpy
Requires-Dist: aicsimageio[bioformats]
Requires-Dist: bioformats-jar
Requires-Dist: SimpleITK
Requires-Dist: pandas
Requires-Dist: h5py
Requires-Dist: opencv-python
Requires-Dist: czifile
Requires-Dist: imagecodecs
Requires-Dist: napari[all]
